<?xml version="1.0" encoding="UTF-8" standalone="yes"?>
<projeto xmlns="http://www.nasajon.com.br/nsjbuild" xmlns:xsi="http://www.w3.org/2001/XMLSchema-instance" xsi:schemaLocation="http://www.nasajon.com.br/nsjbuild nsjBuildProject.xsd ">
    <nome>RPS</nome>
    <path>source\desktop_new\commonfeature\rps\package\rps.dproj</path>
    <dependencias>
        <dependencia>LIMITEDECREDITO</dependencia>
        <dependencia>NSJREPORTEDITOR</dependencia>
        <dependencia>TLB</dependencia>
        <dependencia>NSINTEGRADORGED</dependencia>
        <dependencia>RELATORIOS</dependencia>
        <dependencia>GERADORDEDOCUMENTO</dependencia>
        <dependencia>NSFUNCOESCONTROLES</dependencia>
        <dependencia>NSXEUTIL</dependencia>
        <dependencia>HISTORICOSPADRAO</dependencia>
        <dependencia>LOTERPS</dependencia>
        <dependencia>RPSBASE</dependencia>
        <dependencia>COMMONUTILS_STATIC</dependencia>
        <dependencia>ITENSFATURAMENTOBASE</dependencia>
        <dependencia>ITENSFATURAMENTO</dependencia>
        <dependencia>NSORM</dependencia>
        <dependencia>FINANCEIRO</dependencia>
        <dependencia>CFOP</dependencia>
        <dependencia>DOCUMENTORATEADO</dependencia>
        <dependencia>PROJETOFINANCEIRO</dependencia>
        <dependencia>NSPROXY</dependencia>
        <dependencia>NSJAPI</dependencia>
        <dependencia>OBRA</dependencia>
        <dependencia>NSTRADUCAO</dependencia>
        <dependencia>SERIES</dependencia>
        <dependencia>DOCENGINE</dependencia>
        <dependencia>USUARIO</dependencia>
        <dependencia>ENTIDADESEMPRESARIAIS</dependencia>
    </dependencias>
</projeto>
